setup.py
dsnd1_probability/Binomialdistribution.py
dsnd1_probability/Gaussiandistribution.py
dsnd1_probability/Generaldistribution.py
dsnd1_probability/__init__.py
dsnd1_probability.egg-info/PKG-INFO
dsnd1_probability.egg-info/SOURCES.txt
dsnd1_probability.egg-info/dependency_links.txt
dsnd1_probability.egg-info/not-zip-safe
dsnd1_probability.egg-info/top_level.txt